{"player":{"id":"3251be79-b538-4133-88bc-3b976b68e9ea","name":"David Hake","wins":3,"losses":4,"win_rate":42.9,"fargo":378,"fargo_id":"0A57B3AD-0162-4A5E-948F-B1F0011E29C6","fargo_robustness":"27","fargo_source":"fairmatch-indexsearch-local","fargo_source_url":"https://dashboard.fargorate.com/api/indexsearch?q=<name>","fargo_updated_at":"2026-07-13T22:17:36.775328+00:00","fargo_confidence":"0.99","elo_rating":1493,"elo_peak":1503,"elo_matches":7,"tournaments_played":2,"attendance_streak":0,"best_attendance_streak":1,"average_placement":null,"top_1_finishes":0,"second_place_finishes":0,"third_place_finishes":0,"fourth_place_finishes":0,"top_2_finishes":0,"top_3_finishes":0,"top_4_finishes":0,"placements_counted":0,"cash_won":0.0,"biggest_tournament_cash":0.0,"races_won":3,"races_lost":4,"races_played":7,"racks_won":10,"racks_lost":12,"racks_played":22,"scored_races":7,"rivalry_wins":0,"best_elo_upset_rating_gap":137,"best_elo_upset_probability":31.2,"worst_elo_loss_rating_gap":81,"worst_elo_loss_probability":61.5,"strength_of_schedule":1520,"opponent_win_rate":45.5,"opponent_count":6},"head_to_head":[{"opponent":"Mike Selby","wins":1,"losses":1},{"opponent":"Sourabh Garg","wins":0,"losses":1},{"opponent":"Niko Butt","wins":1,"losses":0},{"opponent":"Lucky Pelonia","wins":0,"losses":1},{"opponent":"Nathan Maines","wins":1,"losses":0},{"opponent":"Isaac Renz","wins":0,"losses":1}]}